scale_sensor_fusion_io/__init__.py
scale_sensor_fusion_io/loaders/__init__.py
scale_sensor_fusion_io/loaders/bs5_loader.py
scale_sensor_fusion_io/loaders/sfs_loader.py
scale_sensor_fusion_io/model_converters/__init__.py
scale_sensor_fusion_io/model_converters/sfs.py
scale_sensor_fusion_io/models/Pose.py
scale_sensor_fusion_io/models/__init__.py
scale_sensor_fusion_io/models/annotations/__init__.py
scale_sensor_fusion_io/models/annotations/attributes.py
scale_sensor_fusion_io/models/annotations/box_2d.py
scale_sensor_fusion_io/models/annotations/cuboid.py
scale_sensor_fusion_io/models/annotations/event.py
scale_sensor_fusion_io/models/annotations/labeled_points.py
scale_sensor_fusion_io/models/annotations/localization_adjustment.py
scale_sensor_fusion_io/models/annotations/object.py
scale_sensor_fusion_io/models/annotations/polygon.py
scale_sensor_fusion_io/models/annotations/polygon_topdown.py
scale_sensor_fusion_io/models/annotations/polyline.py
scale_sensor_fusion_io/models/common.py
scale_sensor_fusion_io/models/paths/__init__.py
scale_sensor_fusion_io/models/paths/attribute_path.py
scale_sensor_fusion_io/models/paths/cuboid_path.py
scale_sensor_fusion_io/models/paths/pose_path.py
scale_sensor_fusion_io/models/paths/spacial_path.py
scale_sensor_fusion_io/models/paths/transformable_path.py
scale_sensor_fusion_io/models/scene.py
scale_sensor_fusion_io/models/sensors/__init__.py
scale_sensor_fusion_io/models/sensors/camera/__init__.py
scale_sensor_fusion_io/models/sensors/camera/camera_distortion.py
scale_sensor_fusion_io/models/sensors/camera/camera_intrinsics.py
scale_sensor_fusion_io/models/sensors/camera/camera_sensor.py
scale_sensor_fusion_io/models/sensors/lidar/__init__.py
scale_sensor_fusion_io/models/sensors/lidar/lidar_sensor.py
scale_sensor_fusion_io/models/sensors/odometry/__init__.py
scale_sensor_fusion_io/models/sensors/odometry/odometry_sensor.py
scale_sensor_fusion_io/models/sensors/points/__init__.py
scale_sensor_fusion_io-0.5.4.dist-info/LICENSE
scale_sensor_fusion_io-0.5.4.dist-info/METADATA
scale_sensor_fusion_io-0.5.4.dist-info/WHEEL
scale_sensor_fusion_io-0.5.4.dist-info/RECORD
