Metadata-Version: 2.3
Name: scale_sensor_fusion_io
Version: 0.5.4
Summary: Library for working with timestamp-based sensor fusion scenes
License: Apache-2.0
Author: Michael Choi
Author-email: michael.choi@scale.com
Requires-Python: >=3.10,<3.12
Classifier: License :: OSI Approved :: Apache Software License
Classifier: Programming Language :: Python :: 3
Classifier: Programming Language :: Python :: 3.10
Classifier: Programming Language :: Python :: 3.11
Requires-Dist: dacite2 (>=2.0.0,<3.0.0)
Requires-Dist: ffmpeg-python (>=0.2.0,<0.3.0)
Requires-Dist: numpy (>=2.2.3,<3.0.0)
Requires-Dist: opencv-python (>=4.7.0.72,<5.0.0.0)
Requires-Dist: pandas (>=2.2.3,<3.0.0)
Requires-Dist: pyturbojpeg (>=1.7.1,<2.0.0)
Requires-Dist: scale-json-binary (>=0.0.7,<0.0.8)
Requires-Dist: scipy (>=1.10.1,<2.0.0)
Requires-Dist: sk-video (>=1.1.10,<2.0.0)
Requires-Dist: tqdm (>=4.65.0,<5.0.0)
Requires-Dist: typing-extensions (>=4.5.0,<5.0.0)
Requires-Dist: ujson (>=5.7.0,<6.0.0)
